pycounts_annanandar/__init__.py
pycounts_annanandar/plotting.py
pycounts_annanandar/pycounts_annanandar.py
pycounts_annanandar-0.1.0.dist-info/LICENSE
pycounts_annanandar-0.1.0.dist-info/METADATA
pycounts_annanandar-0.1.0.dist-info/WHEEL
pycounts_annanandar-0.1.0.dist-info/RECORD
