Metadata-Version: 2.3
Name: pycounts_annanandar
Version: 0.1.0
Summary: Calculate word counts in a text file!
License: MIT
Author: Anna Nandar
Requires-Python: >=3.9,<4.0
Classifier: License :: OSI Approved :: MIT License
Classifier: Programming Language :: Python :: 3
Classifier: Programming Language :: Python :: 3.9
Classifier: Programming Language :: Python :: 3.10
Classifier: Programming Language :: Python :: 3.11
Classifier: Programming Language :: Python :: 3.12
Classifier: Programming Language :: Python :: 3.13
Requires-Dist: matplotlib (>=3.4.3,<4.0.0)
